nrw/__init__.py
nrw/__init__.pyi
nrw/py.typed
pynrw-1.5.2.dist-info/LICENSE
pynrw-1.5.2.dist-info/METADATA
pynrw-1.5.2.dist-info/WHEEL
pynrw-1.5.2.dist-info/top_level.txt
pynrw-1.5.2.dist-info/RECORD
