Metadata-Version: 2.1
Name: pynrw
Version: 1.5.2
Summary: Materialien zu den zentralen NRW-Abiturprüfungen im Fach Informatik ab 2018 implementiert in Python.
Author: realshouzy
License: MIT
Project-URL: Source, https://github.com/realshouzy/pynrw
Keywords: nrw,datastructures,datenstrukturen,algorithms,algorithmen,education,bildung,abitur
Platform: any
Classifier: Programming Language :: Python :: 3 :: Only
Classifier: Programming Language :: Python :: 3.8
Classifier: Programming Language :: Python :: 3.9
Classifier: Programming Language :: Python :: 3.10
Classifier: Programming Language :: Python :: 3.11
Classifier: Programming Language :: Python :: 3.12
Classifier: Programming Language :: Python :: Implementation :: CPython
Classifier: Programming Language :: Python :: Implementation :: PyPy
Classifier: Intended Audience :: Developers
Classifier: Operating System :: OS Independent
Requires-Python: >=3.8
License-File: LICENSE
Requires-Dist: mysql-connector-python
Requires-Dist: pyodbc ; platform_python_implementation == "CPython"
Requires-Dist: pypyodbc ; platform_python_implementation == "PyPy"
Requires-Dist: typing-extensions >=4.4.0 ; python_version < "3.12"
